{
  "description": "Geological Map RGB Mapping Data - Geological Ages and Rock Types by Year",
  "total_colors": 23,
  "rgb_mappings": [
    {
      "rgb": [243, 255, 89],
      "hex": "#f3ff59",
      "rock_type": "Sedimentary rocks or undifferentiated facies"
    },
    {
      "rgb": [255, 243, 231],
      "hex": "#fff3e7",
      "rock_type": "Ice shelf, Extension of the ice shelf"
    },
    {
      "rgb": [231, 231, 231],
      "hex": "#e7e7e7",
      "rock_type": "Inland ice, Glacier"
    },
    {
      "rgb": [113, 243, 166],
      "hex": "#71f3a6",
      "rock_type": "Extrusive volcanic rocks"
    },
    {
      "rgb": [206, 206, 255],
      "hex": "#ceceff",
      "rock_type": "Endogenous rocks (plutonic and/or metamorphic)"
    },
    {
      "rgb": [231, 190, 77],
      "hex": "#e7be4d",
      "rock_type": "Endogenous rocks (plutonic and/or metamorphic)"
    },
    {
      "rgb": [190, 130, 65],
      "hex": "#be8241",
      "rock_type": "Endogenous rocks (plutonic and/or metamorphic)"
    },
    {
      "rgb": [255, 77, 255],
      "hex": "#ff4dff",
      "rock_type": "Endogenous rocks (plutonic and/or metamorphic)"
    },
    {
      "rgb": [255, 154, 231],
      "hex": "#ff9ae7",
      "rock_type": "Sedimentary rocks or undifferentiated facies"
    },
    {
      "rgb": [154, 231, 231],
      "hex": "#9ae7e7",
      "rock_type": "Sedimentary rocks or undifferentiated facies"
    },
    {
      "rgb": [255, 178, 178],
      "hex": "#ffb2b2",
      "rock_type": "Sedimentary rocks or undifferentiated facies"
    },
    {
      "rgb": [255, 178, 49],
      "hex": "#ffb231",
      "rock_type": "Sedimentary rocks or undifferentiated facies"
    },
    {
      "rgb": [255, 24, 24],
      "hex": "#ff1818",
      "rock_type": "Large Igneous Provinces (LIP)"
    },
    {
      "rgb": [255, 178, 219],
      "hex": "#ffb2db",
      "rock_type": "Sedimentary rocks or undifferentiated facies"
    },
    {
      "rgb": [255, 178, 101],
      "hex": "#ffb265",
      "rock_type": "Endogenous rocks (plutonic and/or metamorphic)"
    },
    {
      "rgb": [219, 142, 49],
      "hex": "#db8e31",
      "rock_type": "Endogenous rocks (plutonic and/or metamorphic)"
    },
    {
      "rgb": [255, 154, 130],
      "hex": "#ff9a82",
      "rock_type": "Endogenous rocks (plutonic and/or metamorphic)"
    },
    {
      "rgb": [190, 113, 255],
      "hex": "#be71ff",
      "rock_type": "Sedimentary rocks or undifferentiated facies"
    },
    {
      "rgb": [171, 211, 223],
      "hex": "#abd3df",
      "rock_type": "Sedimentary rocks or undifferentiated facies"
    },
    {
      "rgb": [154, 231, 49],
      "hex": "#9ae731",
      "rock_type": "Extrusive volcanic rocks"
    },
    {
      "rgb": [231, 166, 255],
      "hex": "#e7a6ff",
      "rock_type": "Extrusive volcanic rocks"
    },
    {
      "rgb": [172, 212, 223],
      "hex": "#acd4df",
      "rock_type": "Sedimentary rocks or undifferentiated facies"
    },
    {
      "rgb": [36, 255, 130],
      "hex": "#24ff82",
      "rock_type": "Extrusive volcanic rocks"
    }
  ]
}